easysec/__init__.py
easysec/easysec.py
easysec-0.0.2.dist-info/LICENSE
easysec-0.0.2.dist-info/METADATA
easysec-0.0.2.dist-info/WHEEL
easysec-0.0.2.dist-info/top_level.txt
easysec-0.0.2.dist-info/RECORD
