Metadata-Version: 2.1
Name: easysec
Version: 0.0.2
Summary: Python library to import data from SEC.gov.
Home-page: UNKNOWN
Author: Guillermo Vizcaíno Román
Author-email: <guillevzn@gmail.com>
License: UNKNOWN
Keywords: python,sec,database,API
Platform: UNKNOWN
Classifier: Development Status :: 1 - Planning
Classifier: Intended Audience :: Developers
Classifier: Programming Language :: Python :: 3
Classifier: Operating System :: Unix
Classifier: Operating System :: MacOS :: MacOS X
Classifier: Operating System :: Microsoft :: Windows
Requires-Dist: pandas
